geeeks/Algorithms.py
geeeks/SecurityAlgo.py
geeeks/StringFunctions.py
geeeks/__init__.py
geeeks-0.1.5.dist-info/LICENSE
geeeks-0.1.5.dist-info/METADATA
geeeks-0.1.5.dist-info/WHEEL
geeeks-0.1.5.dist-info/top_level.txt
geeeks-0.1.5.dist-info/RECORD
