Metadata-Version: 2.1
Name: geeeks
Version: 0.1.5
Summary: A package to make your life easy.
Author: yashpra1010 (Yash Prajapati)
Author-email: yashpra1010@gmail.com
Keywords: math,dyanmic programming,greedy,graph,divide and conquer,algorithm,encryption,decryption
Classifier: Programming Language :: Python :: 3
Classifier: License :: OSI Approved :: MIT License
Classifier: Operating System :: OS Independent
Requires-Python: >=3.6
License-File: LICENSE
Requires-Dist: numpy
Requires-Dist: pandas
